{
	"format_version": "1.12.0",
	"minecraft:geometry": [
		{
			"description": {
				"identifier": "geometry.unknown",
				"texture_width": 32,
				"texture_height": 32,
				"visible_bounds_width": 3,
				"visible_bounds_height": 1.5,
				"visible_bounds_offset": [0, 0.25, 0]
			},
			"bones": [
				{
					"name": "root",
					"pivot": [0, 0, 4],
					"cubes": [
						{"origin": [-1, 0, -5], "size": [2, 6, 10], "uv": [0, 0]},
						{"origin": [-1, 1, -9], "size": [2, 5, 4], "uv": [14, 0]},
						{"origin": [0, 6, 0], "size": [0, 2, 5], "uv": [0, 0]},
						{"origin": [0, -3, -1], "size": [0, 3, 6], "uv": [0, 10]}
					]
				},
				{
					"name": "tank",
					"parent": "root",
					"pivot": [0, 0, 0],
					"cubes": [
						{"origin": [-2, -1, 5], "size": [4, 8, 5], "uv": [11, 16]}
					]
				},
				{
					"name": "water",
					"parent": "tank",
					"pivot": [0, -1, 7],
					"cubes": [
						{"origin": [-1, -1, 6], "size": [2, 7, 3], "uv": [0, 19]}
					]
				},
				{
					"name": "holsterFin",
					"parent": "root",
					"pivot": [0, 0, -4],
					"rotation": [0, -35, 0],
					"cubes": [
						{"origin": [0.39273, -2, -2.75442], "size": [3, 2, 0], "pivot": [1.39273, 2, -3.75442], "rotation": [0, -55, 0], "uv": [0, 2]}
					]
				}
			]
		}
	]
}